rango/__init__.py
rango_framework-0.1.0.dist-info/WHEEL
rango_framework-0.1.0.dist-info/METADATA
rango_framework-0.1.0.dist-info/RECORD
